src/microcode.sv
`define CTRL_WIDTH 32
`define CTRL_DEPTH 256

module Microcode(clk, ctrl, opcode, eos, sos);
	
input clk;
output reg [`CTRL_WIDTH:0] ctrl = 0;
input [5:0] opcode;
/* End of segment: signals the outer system that its execution is finished, and will wait until a sos signal is received */
output eos;
assign eos = ctrl[`CTRL_WIDTH]; /* It's the very last bit of the control bus */
/* Start of segment: triggers the execution of the next segment */
input sos;

/* Local Variables: */
reg [7:0] code_ip = 0;
reg [`CTRL_WIDTH:0] code [0:`CTRL_DEPTH];
reg [7:0] seg_start [10]; /* Start of the segment */
integer segment_counter = 0;
integer microinstr_ctr = 0;
integer microunit_running = 1;

task check_microcode_running; begin
	microunit_running = opcode == ~6'h0 ? 0 : 1;
end endtask

always@(posedge clk) begin
	/* Check for invalid/halt opcode: */
	check_microcode_running;
	if(microunit_running && code_ip != 'hFF && !eos) begin
		/* Only continue sequentially when EOS is 0 */
		ctrl = code[code_ip];
		code_ip = code_ip + 1;
	 end else begin end; /* Microcode unit is frozen. Needs to be restarted */
end

always@(posedge sos) begin
	check_microcode_running;
	/* Jump to segment before fetching control: */
	if(microunit_running) begin
		code_ip = seg_start[opcode];
		ctrl = code[code_ip];
	end
end

task microinstr;
	input reg [31:0] control;
	input integer is_sos; /* Is start of segment? */
	input integer is_eos; /* Is end of segment? */
begin
	/* Create Segment: */
	if(is_sos) begin
		seg_start[segment_counter] = microinstr_ctr;
		segment_counter = segment_counter + 1;
	end
	
	/* Generate Segment Terminator signal: */
	code[microinstr_ctr] = {is_eos ? 1'b1 : 1'b0, control};
	microinstr_ctr = microinstr_ctr + 1;
end endtask

task microinstr_finish; begin
	/* Fill the rest with 0s in order to keep the CPU frozen */
	for(microinstr_ctr=microinstr_ctr; microinstr_ctr < `CTRL_DEPTH; microinstr_ctr++) 
		code[microinstr_ctr] = 0;
	/* Fill the rest of the segments with invalid pointers */
	for(segment_counter = segment_counter; segment_counter < 10; segment_counter++)
		seg_start[segment_counter] = ~0;
end endtask

/************************** MICROCODE BEGIN SECTION **************************/
initial begin
	/* Program Microcode for each instruction here: */
	microinstr(32'b1100011000, 1, 0); /* LW */
	microinstr(32'b1100011000, 0, 0); /* LW */
	microinstr(32'b1100011000, 0, 0); /* LW */
	microinstr(32'b1100011000, 0, 1); /* LW */
	microinstr(32'b0110000000, 1, 1); /* SW */
	/* ADD */
	/* SUB */
	/* AND */
	/* OR */
	/* SLT */
	/* BEQ */
	/* JMP */
	microinstr_finish;
end
endmodule

src/datapath.sv
`include "microcode.sv"

module Progmem(address, instruction);
	input [31:0] address;
	output [31:0] instruction;
	
	reg [31:0] mem [0:256];
	assign instruction = mem[address];
	
	/***************** Fill progmem here *****************/
	initial begin
		mem[0] = {6'h0, 5'h0,5'h0,16'h0}; /* LW */
		mem[1] = {6'h1, 5'h0,5'h0,16'h0}; /* SW */
		mem[2] = {6'h0, 5'h0,5'h0,16'h0}; /* LW */
		mem[3] = {6'h1, 5'h0,5'h0,16'h0}; /* SW */
		mem[4] = {6'h0, 5'h0,5'h0,16'h0}; /* LW */
		/* ADD */
		/* SUB */
		/* BEQ */
		/* JMP */
		
		/* End of memory: */
		mem[5] = {~6'h0, 26'h0}; /* Invalid Op */
	end
endmodule

module Datamem(address, writedata, readdata, mrd, mwr);
	input [31:0]address, writedata;
	input mrd, mwr;
	output reg [31:0] readdata;
	reg [31:0] mem [0:256]; 
	
	assign readdata = mrd ? mem[address] : 'hz;
	
	always@(posedge mwr) if(mwr) mem[address] = writedata;
		
	initial begin
		integer i;
		for(i = 0; i < 256; i++) mem[i] = 'hAC;
	end
endmodule

module Registers(readreg1, readreg2, writereg, writedata, regout1, regout2, regwr);
	input [4:0] readreg1,readreg2, writereg;
	input [31:0] writedata;
	output [31:0] regout1,regout2;
	input regwr;
	
	reg [31:0] regfile [0:32];
	
	assign regout1 = regfile[readreg1];
	assign regout2 = regfile[readreg2];
	
	initial begin
		integer i;
		for(i = 0;i < 32; i++) regfile[i] = 0;
	end
	
	always@(posedge regwr) if(regwr) regfile[writereg] = writedata;
endmodule

module ALU(opA, opB, func, zero, result);
	input [31:0] opA, opB;
	input [3:0] func;
	output zero;
	output [31:0] result;
	assign result = 
		func == 4'b0000 ? opA & opB : 
		func == 4'b0001 ? opA | opB :
		func == 4'b0010 ? opA + opB :
		func == 4'b0110 ? opA - opB :
		func == 4'b0111 ? (opA < opB ? 1 : 0) :
		func == 4'b1100 ? ~(opA | opB) : 'hX;
	assign zero = !result ? 1 : 0;
endmodule

module datapath;
	/* Generate clock: */
	reg clk; always #1 clk = en_clk ? ~clk : clk;
	reg en_clk;
	
	/* Instantiate microcode controller: */
	wire [`CTRL_WIDTH:0] ctrl;
	wire microcode_done; /* Signals when the microcode has finished executing a certain segment */
	reg microcode_restart; /* Triggers the execution of the microcode unit */
	Microcode microcode(clk, ctrl, instruction[31:26], microcode_done, microcode_restart);
	
	/* Control wires (connect it to microcode controller): */
	wire eip_inc = microcode_done;
	wire regdst = ctrl[0];
	wire jump = ctrl[1];
	wire branch = ctrl[2];
	wire memread = ctrl[3];
	wire memtoreg = ctrl[4];
	wire [1:0] aluop = ctrl[6:5];
	wire memwrite = ctrl[7];
	wire alusrc = ctrl[8];
	wire regwrite = ctrl[9];
	
	/* Program Counter: */
	reg [31:0] eip = 0;
	wire [31:0] eip_next = eip + 1;
	
	always@(posedge eip_inc or posedge clk) begin
		/* Trigger microcode execution: */
		if(eip_inc) begin
			eip <= 
				jump ? {eip_next[31:28], (instruction[25:0] << 2)} : 
				branch & zero ?  eip_next + ({16'h0, instruction[15:0]} << 2) : eip_next;
			microcode_restart <= 1;
		end
	end
	
	always@(negedge clk) microcode_restart = 0; /* Bring the microcode trigger down */
	
	/* Program Memory: */
	wire [31:0] instruction;
	Progmem progmem(eip, instruction);
	
	/* Registers: */
	wire [4:0] readreg1 = instruction[25:21];
	wire [4:0] readreg2 = instruction[20:16];
	wire [4:0] writereg = regdst ? instruction[15:11] : instruction[20:16];
	wire [31:0] prog_writedata = memtoreg ? readdata : result;
	wire [31:0] regout1, regout2;
	Registers registers(readreg1, readreg2, writereg, prog_writedata, regout1, regout2, regwrite);
	
	/* ALU: */
	wire [31:0] opA = regout1;
	wire [31:0] opB = alusrc ? {16'h0,instruction[15:0]} : regout2;
	wire [3:0] func = 
		/* ALU Control: */
		!aluop   ? 4'b0010 : 
		aluop[0] ? 4'b0110 :
		aluop[1] ? 
			( 
			  instruction[5:0] == 4'b0000 ? 4'b0010 :
			  instruction[5:0] == 4'b0010 ? 4'b0110 :
			  instruction[5:0] == 4'b0100 ? 4'b0000 :
			  instruction[5:0] == 4'b0101 ? 4'b0001 :
			  instruction[5:0] == 4'b1010 ? 4'b0111 :
			  'hx
			) 
		: 'hx;
	wire zero;
	wire [31:0] result;
	ALU alu(opA, opB, func, zero, result);
	
	/* Data Memory: */
	wire [31:0] address = result;
	wire [31:0] data_writedata = regout2;
	wire [31:0] readdata;
	Datamem datamem(address, data_writedata, readdata, memread, memwrite);
	
	/* Testbench: */
	initial begin
		$dumpfile("datapath.vcd");
		$dumpvars(0, datapath);
		
		/* Initialize: */
		microcode_restart = 0;
		en_clk = 0;
		clk = 0;
		
		/* Kickstart: */
		#1;
		clk = 1;
		microcode_restart = 1;
		en_clk = 1;
		
		/* Let it run for a while: */
		#50 $finish;
	end
endmodule

waves/datapath.vcd
$date
	Wed Jun 22 18:19:54 2016
$end
$version
	Icarus Verilog
$end
$timescale
	1s
$end
$scope module datapath $end
$var wire 32 ! address [31:0] $end
$var wire 32 " data_writedata [31:0] $end
$var wire 1 # eip_inc $end
$var wire 32 $ opA [31:0] $end
$var wire 1 % zero $end
$var wire 5 & writereg [4:0] $end
$var wire 32 ' result [31:0] $end
$var wire 1 ( regwrite $end
$var wire 32 ) regout2 [31:0] $end
$var wire 32 * regout1 [31:0] $end
$var wire 1 + regdst $end
$var wire 5 , readreg2 [4:0] $end
$var wire 5 - readreg1 [4:0] $end
$var wire 32 . readdata [31:0] $end
$var wire 32 / prog_writedata [31:0] $end
$var wire 32 0 opB [31:0] $end
$var wire 1 1 microcode_done $end
$var wire 1 2 memwrite $end
$var wire 1 3 memtoreg $end
$var wire 1 4 memread $end
$var wire 1 5 jump $end
$var wire 32 6 instruction [31:0] $end
$var wire 4 7 func [3:0] $end
$var wire 32 8 eip_next [31:0] $end
$var wire 33 9 ctrl [32:0] $end
$var wire 1 : branch $end
$var wire 1 ; alusrc $end
$var wire 2 < aluop [1:0] $end
$var reg 1 = clk $end
$var reg 32 > eip [31:0] $end
$var reg 1 ? en_clk $end
$var reg 1 @ microcode_restart $end
$scope module alu $end
$var wire 4 A func [3:0] $end
$var wire 32 B opA [31:0] $end
$var wire 32 C opB [31:0] $end
$var wire 1 % zero $end
$var wire 32 D result [31:0] $end
$upscope $end
$scope module datamem $end
$var wire 32 E address [31:0] $end
$var wire 1 4 mrd $end
$var wire 1 2 mwr $end
$var wire 32 F writedata [31:0] $end
$var wire 32 G readdata [31:0] $end
$scope begin $unm_blk_11 $end
$var integer 32 H i [31:0] $end
$upscope $end
$upscope $end
$scope module microcode $end
$var wire 1 = clk $end
$var wire 6 I opcode [5:0] $end
$var wire 1 @ sos $end
$var wire 1 1 eos $end
$var reg 8 J code_ip [7:0] $end
$var reg 33 K ctrl [32:0] $end
$var integer 32 L microinstr_ctr [31:0] $end
$var integer 32 M microunit_running [31:0] $end
$var integer 32 N segment_counter [31:0] $end
$scope task check_microcode_running $end
$upscope $end
$scope task microinstr $end
$var reg 32 O control [31:0] $end
$var integer 32 P is_eos [31:0] $end
$var integer 32 Q is_sos [31:0] $end
$upscope $end
$scope task microinstr_finish $end
$upscope $end
$upscope $end
$scope module progmem $end
$var wire 32 R address [31:0] $end
$var wire 32 S instruction [31:0] $end
$upscope $end
$scope module registers $end
$var wire 5 T readreg1 [4:0] $end
$var wire 5 U readreg2 [4:0] $end
$var wire 32 V regout1 [31:0] $end
$var wire 32 W regout2 [31:0] $end
$var wire 1 ( regwr $end
$var wire 32 X writedata [31:0] $end
$var wire 5 Y writereg [4:0] $end
$scope begin $unm_blk_12 $end
$var integer 32 Z i [31:0] $end
$upscope $end
$upscope $end
$upscope $end
$enddefinitions $end
#0
$dumpvars
b100000 Z
b0 Y
b0 X
b0 W
b0 V
b0 U
b0 T
b0 S
b0 R
b1 Q
b1 P
b110000000 O
b1010 N
b1 M
b100000000 L
b0 K
b0 J
b0 I
b100000000 H
bz G
b0 F
b0 E
b0 D
b0 C
b0 B
b10 A
0@
0?
b0 >
0=
b0 <
0;
0:
b0 9
b1 8
b10 7
b0 6
05
04
03
02
01
b0 0
b0 /
bz .
b0 -
b0 ,
0+
b0 *
b0 )
0(
b0 '
b0 &
1%
b0 $
0#
b0 "
b0 !
$end
#1
0%
b10101100 !
b10101100 E
b10101100 '
b10101100 D
b10101100 $
b10101100 B
b10101100 *
b10101100 V
b10101100 "
b10101100 F
b10101100 )
b10101100 W
b10101100 /
b10101100 X
b10101100 .
b10101100 G
1(
1;
13
14
b0 J
b1100011000 9
b1100011000 K
1?
1@
1=
#2
0@
0=
#3
b1 J
1=
#4
0=
#5
b10 J
1=
#6
0=
#7
b11 J
1=
#8
0=
#9
bz .
bz G
0(
12
03
04
b1 I
1@
b10 8
b100000000000000000000000000 6
b100000000000000000000000000 S
b1 >
b1 R
1#
11
b100 J
b100000000000000000000000110000000 9
b100000000000000000000000110000000 K
1=
#10
0@
0=
#11
b10101100 .
b10101100 G
0#
01
1(
02
13
14
b1100011000 9
b1100011000 K
b0 J
b0 I
1@
b11 8
b0 6
b0 S
b10 >
b10 R
1=
#12
0@
0=
#13
b1 J
1=
#14
0=
#15
b10 J
1=
#16
0=
#17
b11 J
1=
#18
0=
#19
bz .
bz G
0(
12
03
04
b1 I
1@
b100 8
b100000000000000000000000000 6
b100000000000000000000000000 S
b11 >
b11 R
1#
11
b100 J
b100000000000000000000000110000000 9
b100000000000000000000000110000000 K
1=
#20
0@
0=
#21
b10101100 .
b10101100 G
0#
01
1(
02
13
14
b1100011000 9
b1100011000 K
b0 J
b0 I
1@
b101 8
b0 6
b0 S
b100 >
b100 R
1=
#22
0@
0=
#23
b1 J
1=
#24
0=
#25
b10 J
1=
#26
0=
#27
b11 J
1=
#28
0=
#29
b0 M
b111111 I
1@
b110 8
b11111100000000000000000000000000 6
b11111100000000000000000000000000 S
b101 >
b101 R
1#
11
b100 J
b100000000000000000000001100011000 9
b100000000000000000000001100011000 K
1=
#30
0@
0=
#31
x%
bx /
bx X
bx .
bx G
bx !
bx E
bx '
bx D
b0xxxxxxxxxxxxxxxx 0
b0xxxxxxxxxxxxxxxx C
bx &
bx Y
b0x M
bx "
bx F
bx )
bx W
bx ,
bx U
bx $
bx B
bx *
bx V
bx -
bx T
bx I
1@
b111 8
bx 6
bx S
b110 >
b110 R
1=
#32
0@
0=
#33
1@
b1000 8
b111 >
b111 R
1=
#34
0@
0=
#35
1@
b1001 8
b1000 >
b1000 R
1=
#36
0@
0=
#37
1@
b1010 8
b1001 >
b1001 R
1=
#38
0@
0=
#39
1@
b1011 8
b1010 >
b1010 R
1=
#40
0@
0=
#41
1@
b1100 8
b1011 >
b1011 R
1=
#42
0@
0=
#43
1@
b1101 8
b1100 >
b1100 R
1=
#44
0@
0=
#45
1@
b1110 8
b1101 >
b1101 R
1=
#46
0@
0=
#47
1@
b1111 8
b1110 >
b1110 R
1=
#48
0@
0=
#49
1@
b10000 8
b1111 >
b1111 R
1=
#50
0@
0=
#51
1@
b10001 8
b10000 >
b10000 R
1=
