src/microcode.sv
`define CTRL_WIDTH 32
`define FUNC_WIDTH 32
`define CTRL_DEPTH 256
`define SEGMENT_MAXCOUNT 256
`define CTRL_DEPTH_ENC ($clog2(`CTRL_DEPTH) - 1)
`define SEGMENT_MAXCOUNT_ENC ($clog2(`SEGMENT_MAXCOUNT) - 1)
`define CALLSTACK_SIZE 256

/* Change this macro to 0 to convert the microcode unit 
 * into a multicycle microcode unit */
`define SINGLECYCLE 0

module Microcode(clk, ctrl, opcode, eos, sos);

/************************* PORT DEFINITIONS *************************/
input clk;
output reg [`CTRL_WIDTH:0] ctrl = 0;
input [5:0] opcode;
/* End of segment: signals the outer system that its execution is finished, and will wait until a sos signal is received */
output eos;
assign eos = ctrl[`CTRL_WIDTH]; /* It's the very last bit of the control bus */
/* Start of segment: triggers the execution of the next segment */
input sos;

/************************* LOCAL VARIABLES *************************/
reg [`CTRL_DEPTH_ENC:0] code_ip = 0; /* Microcode instruction pointer */
reg [`CTRL_DEPTH_ENC:0] call_stack[`CALLSTACK_SIZE];
reg [`CTRL_DEPTH_ENC:0] stack_ptr = 0;
reg [`FUNC_WIDTH + `CTRL_WIDTH + 1:0] code [0:`CTRL_DEPTH]; /* Microcode memory */
reg [`SEGMENT_MAXCOUNT_ENC:0] seg_start [`SEGMENT_MAXCOUNT]; /* Start of the segment */
reg [`SEGMENT_MAXCOUNT_ENC:0] int_seg_start [`SEGMENT_MAXCOUNT]; /* Start of the segment (for functional microcode memory) */
integer segment_counter = 0;
integer int_segment_counter = 0;
integer microinstr_ctr = 0;
reg microunit_running = 1;
reg microunit_init = 0;

/************************* FLAGS *************************/
reg flag_jmp = 0;
reg [`CTRL_DEPTH_ENC:0] flag_jmp_addr = ~0;
reg zero = 0;

/************************* SYSTEM PROCESSES *************************/

/** Execute instruction:  **/
reg [1:0] instruction_type = 0;
reg [`FUNC_WIDTH-1:0] func_fmt = 0;

task schedule_jmp;
	input [`CTRL_DEPTH_ENC:0] new_addr;
begin 
	flag_jmp_addr = new_addr;
	flag_jmp = 1;
end endtask

task push_stack;
	input [`CTRL_DEPTH_ENC:0] address;
begin
	call_stack[stack_ptr] = address;
	stack_ptr = stack_ptr + 1;
end endtask

task pop_stack; begin
	if(stack_ptr > 0) begin
		stack_ptr = stack_ptr - 1;
		schedule_jmp(call_stack[stack_ptr]);
	end
end endtask

task exec_microinstruction;
	input [`CTRL_DEPTH_ENC:0] address;
begin
	instruction_type = code[address][`CTRL_WIDTH + 2:`CTRL_WIDTH + 1];
	func_fmt = code[address][`FUNC_WIDTH + `CTRL_WIDTH + 1:(`FUNC_WIDTH + `CTRL_WIDTH + 1) - 30];
	case(func_fmt[`FUNC_WIDTH-1:`FUNC_WIDTH-4])
		4'b0000: begin /* No op */ end
		4'b0001: begin
			/* Jump to OPCODE segment on the next cycle */
			schedule_jmp(seg_start[func_fmt[`FUNC_WIDTH - 6:0]]);
			push_stack(address + 1);
		end
		4'b0010: begin
			/* Jump to INSTRUCTION/FUNCTION segment on the next cycle */
			schedule_jmp(int_seg_start[func_fmt[`FUNC_WIDTH - 6:0]]);
			push_stack(address + 1);
		end 
	endcase
	/* Fetch control from microcode memory: */
	ctrl = code[address][`CTRL_WIDTH:0];
end endtask

always@(posedge clk) begin
	/* Check for invalid/halt opcode: */
	check_microcode_running;
	if(microunit_running && code_ip != 'hFF && !sos && microunit_init) begin
		/* Check flags first: */
		if(flag_jmp) begin /* Jump flag */
			/* We found an inconditional branch (for the microcode unit, not datapath) */
			code_ip = flag_jmp_addr;
			flag_jmp = 0;
		end else begin
			/* Check if we reached End of Segment: */
			if(eos) begin
				/* We need to pop the stack */
				pop_stack;
			end else begin
				/* Otherwise continue sequential execution: */
				code_ip = code_ip + 1;
			end
		end
		/* Execute microinstruction: */
		exec_microinstruction(code_ip);
	end else begin end; /* Microcode unit is frozen. Needs to be restarted */
end

always@(posedge sos) begin
	check_microcode_running;
	microunit_init = 1;
	/* Jump to segment before fetching control: */
	if(microunit_running) begin
		code_ip = seg_start[opcode];
		/* Execute microinstruction: */
		exec_microinstruction(code_ip);
	end
end


/************************* FUNCTIONS *************************/
task check_microcode_running; begin
	microunit_running = opcode == ~6'h0 ? 1'b0 : 1'b1;
end endtask

task microinstr;
	input reg [`CTRL_WIDTH - 1:0] control;
	input reg [`FUNC_WIDTH - 1:0] func;
	input integer is_sos; /* Is start of segment? */
	input integer is_eos; /* Is end of segment? */
	input reg [1:0] seg_type; /* Is this segment dedicated for opcode execution, is it for FSM exec or is it data? */
begin
	/* Create Segment: */
	if(is_sos) begin
		if(!seg_type) begin /* Install into opcode segment: */
			seg_start[segment_counter] = microinstr_ctr;
			segment_counter = segment_counter + 1;
		end else if(seg_type == 1) begin /* Install into function code segment: */
			int_seg_start[int_segment_counter] = microinstr_ctr;
			int_segment_counter = int_segment_counter + 1;	
		end
	end
	
	/* Generate Segment Terminator signal: */
	code[microinstr_ctr] = {func, seg_type, is_eos ? 1'b1 : 1'b0, control};
	microinstr_ctr = microinstr_ctr + 1;
end endtask

task microinstr_finish; begin
	/* Fill the rest with 0s in order to keep the CPU frozen */
	for(microinstr_ctr = microinstr_ctr; microinstr_ctr < `CTRL_DEPTH; microinstr_ctr++) 
		code[microinstr_ctr] = 0;
		
	/* Fill the rest of the segment memory with invalid pointers */
	for(segment_counter = segment_counter; segment_counter < `SEGMENT_MAXCOUNT; segment_counter++)
		seg_start[segment_counter] = ~0;
	for(int_segment_counter = int_segment_counter; int_segment_counter < `SEGMENT_MAXCOUNT; int_segment_counter++)
		int_seg_start[int_segment_counter] = ~0;
end endtask

/************************** MICROCODE BEGIN SECTION **************************/
initial begin
	/* Program Microcode for each instruction here: */
if(`SINGLECYCLE) begin
	microinstr(32'b1100011000, 0, 1, 1); /* LW */
	microinstr(32'b0110000000, 0, 1, 1); /* SW */
	/* ADD */
	/* SUB */
	/* AND */
	/* OR */
	/* SLT */
	/* BEQ */
	/* JMP */
end else begin
	microinstr(32'b0000000000000001, {4'b0001, 28'd2}, 1, 0, 0); /* LW and jmp to segment 2 */
	microinstr(32'b0000000000000001, 0, 0, 1, 0); /* Then go idle */
	
	microinstr(32'b0000000000000001, {4'b0001, 28'd3}, 1, 0, 0); /* LW and jmp to segment 3 */
	microinstr(32'b0000000000000001, 0, 0, 1, 0); /* then return (pop stack) */
	
	microinstr(32'b0000000000000001, {4'b0001, 28'd1}, 1, 0, 0); /* LW and jmp to segment 1 */
	microinstr(32'b0000000000000001, 0, 0, 1, 0); /* then return (pop stack) */
	
	microinstr(32'b0000000000000001, 0, 1, 1, 0); /* LW then return (pop stack) */
	
	microinstr(32'b0000000001001010, 0, 1, 1, 0); /* SW */
	/* ADD */
	/* SUB */
	/* AND */
	/* OR */
	/* SLT */
	/* BEQ */
	/* JMP */
end
	microinstr_finish;
end
endmodule

src/datapath_multicycle.sv
`include "microcode.sv"

module PC(ip_next, pc_wr, ip);
	input [31:0] ip_next;
	input pc_wr;
	output reg [31:0] ip = 0;
	always@(posedge pc_wr) ip = ip_next;
endmodule

module Memory(address, data_in, data_out, memread, memwrite);
	input [31:0] address;
	input [31:0] data_in;
	output [31:0] data_out;
	input memread, memwrite; 
	
	reg [31:0] memory [0:256];
	
	assign data_out = memread ? memory[address] : 'hZ;
	always@(posedge memwrite) memory[address] = data_in;
		
	initial begin
		memory[0] = {6'h0, 5'h0,5'h0,16'h0}; /* LW */
		memory[1] = {6'h1, 5'h0,5'h0,16'h0}; /* SW */
		memory[2] = {6'h0, 5'h0,5'h0,16'h0}; /* LW */
		memory[3] = {6'h1, 5'h0,5'h0,16'h0}; /* SW */
		memory[4] = {6'h0, 5'h0,5'h0,16'h0}; /* LW */
		/* ADD */
		/* SUB */
		/* BEQ */
		/* JMP */
		
		/* End of memory: */
		memory[5] = {~6'h0, 26'h0}; /* Invalid Op */
	end
endmodule

module InstructionReg(instr_in, instr_out, irwrite);
	input [31:0] instr_in;
	output reg [31:0] instr_out = 0;
	input irwrite;
	
	always@(posedge irwrite) instr_out = instr_in;
endmodule

module MDR(clk, data_in, data_out);
	input clk;
	input [31:0] data_in;
	output reg [31:0] data_out = 0;
	
	always@(posedge clk) data_out = data_in;
endmodule

module Registers(clk, readreg1, readreg2, writereg, writedata, outA, outB, regwr);
	input clk;
	input [4:0] readreg1,readreg2, writereg;
	input [31:0] writedata;
	output reg [31:0] outA = 0;
	output reg [31:0] outB = 0;
	input regwr;
	
	reg [31:0] regfile [0:32];
	
	always@(posedge clk) begin
		outA = regfile[readreg1];
		outB = regfile[readreg2];	
	end
	
	initial begin
		integer i;
		for(i = 0; i < 32; i++) regfile[i] = 0;
	end
	
	always@(posedge regwr) if(regwr) regfile[writereg] = writedata;
endmodule

module ALU(clk, opA, opB, func, zero, result, aluout);
	input clk;
	input [31:0] opA, opB;
	input [3:0] func;
	output zero;
	output [31:0] result;
	output reg [31:0] aluout = 0;
	assign result = 
		func == 4'b0000 ? opA & opB : 
		func == 4'b0001 ? opA | opB :
		func == 4'b0010 ? opA + opB :
		func == 4'b0110 ? opA - opB :
		func == 4'b0111 ? (opA < opB ? 1 : 0) :
		func == 4'b1100 ? ~(opA | opB) : 'hX;
	assign zero = !result ? 1 : 0;
	
	always@(posedge clk) aluout = result;
endmodule

module datapath_multicycle;
	/* Generate clock: */
	reg clk; always #1 clk = en_clk ? ~clk : clk;
	reg en_clk;
	
	/* Instantiate microcode controller: */
	wire [`CTRL_WIDTH:0] ctrl;
	wire microcode_done; /* Signals when the microcode has finished executing a certain segment */
	reg microcode_restart; /* Triggers the execution of the microcode unit */
	Microcode microcode(clk, ctrl, instr_out[31:26], microcode_done, microcode_restart);
	
	/* Bring the microcode trigger down every negative clock edge: */
	always@(negedge clk) microcode_restart <= 0;
	
	/* Control wires (connect it to microcode controller): */
	wire pcwritecond = ctrl[0];
	wire pcwrite = ctrl[1];
	wire iord = ctrl[2];
	wire memread = ctrl[3];
	wire memwrite = ctrl[4];
	wire memtoreg = ctrl[5];
	wire irwrite = ctrl[6];
	wire [1:0] pcsource = ctrl[8:7];
	wire [1:0] aluop = ctrl[10:9];
	wire [1:0] alusrcb = ctrl[12:11];
	wire alusrca = ctrl[13];
	wire regwrite = ctrl[14];
	wire regdst = ctrl[15];
	
	/* Program Counter: */
	wire [31:0] ip_next = pcsource == 2'b00 ? result : pcsource == 2'b01 ? aluout : pcsource == 2'b10 ? instr_out[25:0] << 2 : 0;
	wire [31:0] ip;
	wire pc_wr = (zero & pcwritecond) | pcwrite;
	PC pc(ip_next, pc_wr, ip);
	
	/* Memory: */
	wire [31:0] mem_addr = iord ? aluout : ip;
	wire [31:0] mem_data_in = outB;
	wire [31:0] mem_data_out;
	Memory memory(mem_addr, mem_data_in, mem_data_out, memread, memwrite);
	
	/* Instruction Register: */
	wire [31:0] instr_in = mem_data_out;
	wire [31:0] instr_out;
	InstructionReg instructionReg(instr_in, instr_out, irwrite);
	
	/* Memory Data Register: */
	wire [31:0] mdr_data_in = mem_data_out;
	wire [31:0] mdr_data_out;
	MDR mdr(clk, mdr_data_in, mdr_data_out);
	
	/* Registers: */
	wire [4:0]  readreg1 = instr_out[25:21];
	wire [4:0]  readreg2 = instr_out[20:16];
	wire [4:0]  writereg = regdst ? instr_out[15:11] : instr_out[20:16];
	wire [31:0] writedata = memtoreg ? mdr_data_out : aluout;
	wire [31:0] outA, outB;
	Registers   registers(clk, readreg1, readreg2, writereg, writedata, outA, outB, regwrite);
	
	/* ALU: */
	wire [31:0] opA = alusrca ? outA : ip;
	wire [31:0] opB = alusrcb == 2'b00 ? outB : alusrcb == 2'b01 ? 1 : alusrcb == 2'b10 ? {16'h0,instr_out[15:11]} : {16'h0,instr_out[15:11]} << 2;
	wire [3:0] func =
		/* ALU Control: */
		!aluop   ? 4'b0010 :
		aluop[0] ? 4'b0110 :
		aluop[1] ?
			(
			  instr_out[5:0] == 4'b0000 ? 4'b0010 :
			  instr_out[5:0] == 4'b0010 ? 4'b0110 :
			  instr_out[5:0] == 4'b0100 ? 4'b0000 :
			  instr_out[5:0] == 4'b0101 ? 4'b0001 :
			  instr_out[5:0] == 4'b1010 ? 4'b0111 :
			  'hX
			)
		: 'hX;
	wire zero;
	wire [31:0] result;
	wire [31:0] aluout;
	ALU alu(clk, opA, opB, func, zero, result, aluout);
	
	/* Testbench: */
	initial begin
		$dumpfile("datapath_multicycle.vcd");
		$dumpvars(0, datapath_multicycle);
		
		/* Initialize: */
		microcode_restart = 0;
		en_clk = 0;
		clk = 0;
		
		/* Kickstart: */
		#1;
		clk = 1;
		en_clk = 1;
		microcode_restart = 1;
		
		/* Let it run for a while: */
		#50 $finish;
	end
endmodule

waves/datapath_multicycle.vcd
$date
	Fri Jun 24 00:46:15 2016
$end
$version
	Icarus Verilog
$end
$timescale
	1s
$end
$scope module datapath_multicycle $end
$var wire 32 ! instr_in [31:0] $end
$var wire 32 " mdr_data_in [31:0] $end
$var wire 32 # mem_data_in [31:0] $end
$var wire 1 $ pc_wr $end
$var wire 1 % zero $end
$var wire 5 & writereg [4:0] $end
$var wire 32 ' writedata [31:0] $end
$var wire 32 ( result [31:0] $end
$var wire 1 ) regwrite $end
$var wire 1 * regdst $end
$var wire 5 + readreg2 [4:0] $end
$var wire 5 , readreg1 [4:0] $end
$var wire 1 - pcwritecond $end
$var wire 1 . pcwrite $end
$var wire 2 / pcsource [1:0] $end
$var wire 32 0 outB [31:0] $end
$var wire 32 1 outA [31:0] $end
$var wire 32 2 opB [31:0] $end
$var wire 32 3 opA [31:0] $end
$var wire 1 4 microcode_done $end
$var wire 1 5 memwrite $end
$var wire 1 6 memtoreg $end
$var wire 1 7 memread $end
$var wire 32 8 mem_data_out [31:0] $end
$var wire 32 9 mem_addr [31:0] $end
$var wire 32 : mdr_data_out [31:0] $end
$var wire 1 ; irwrite $end
$var wire 32 < ip_next [31:0] $end
$var wire 32 = ip [31:0] $end
$var wire 1 > iord $end
$var wire 32 ? instr_out [31:0] $end
$var wire 4 @ func [3:0] $end
$var wire 33 A ctrl [32:0] $end
$var wire 2 B alusrcb [1:0] $end
$var wire 1 C alusrca $end
$var wire 32 D aluout [31:0] $end
$var wire 2 E aluop [1:0] $end
$var reg 1 F clk $end
$var reg 1 G en_clk $end
$var reg 1 H microcode_restart $end
$scope module alu $end
$var wire 1 F clk $end
$var wire 4 I func [3:0] $end
$var wire 32 J opA [31:0] $end
$var wire 32 K opB [31:0] $end
$var wire 1 % zero $end
$var wire 32 L result [31:0] $end
$var reg 32 M aluout [31:0] $end
$upscope $end
$scope module instructionReg $end
$var wire 32 N instr_in [31:0] $end
$var wire 1 ; irwrite $end
$var reg 32 O instr_out [31:0] $end
$upscope $end
$scope module mdr $end
$var wire 1 F clk $end
$var wire 32 P data_in [31:0] $end
$var reg 32 Q data_out [31:0] $end
$upscope $end
$scope module memory $end
$var wire 32 R address [31:0] $end
$var wire 32 S data_in [31:0] $end
$var wire 1 7 memread $end
$var wire 1 5 memwrite $end
$var wire 32 T data_out [31:0] $end
$upscope $end
$scope module microcode $end
$var wire 1 F clk $end
$var wire 6 U opcode [5:0] $end
$var wire 1 H sos $end
$var wire 1 4 eos $end
$var reg 8 V code_ip [7:0] $end
$var reg 33 W ctrl [32:0] $end
$var reg 1 X flag_jmp $end
$var reg 8 Y flag_jmp_addr [7:0] $end
$var reg 32 Z func_fmt [31:0] $end
$var reg 2 [ instruction_type [1:0] $end
$var reg 1 \ microunit_init $end
$var reg 1 ] microunit_running $end
$var reg 8 ^ stack_ptr [7:0] $end
$var reg 1 _ zero $end
$var integer 32 ` int_segment_counter [31:0] $end
$var integer 32 a microinstr_ctr [31:0] $end
$var integer 32 b segment_counter [31:0] $end
$scope task check_microcode_running $end
$upscope $end
$scope task exec_microinstruction $end
$var reg 8 c address [7:0] $end
$upscope $end
$scope task microinstr $end
$var reg 32 d control [31:0] $end
$var reg 32 e func [31:0] $end
$var reg 2 f seg_type [1:0] $end
$var integer 32 g is_eos [31:0] $end
$var integer 32 h is_sos [31:0] $end
$upscope $end
$scope task microinstr_finish $end
$upscope $end
$scope task pop_stack $end
$upscope $end
$scope task push_stack $end
$var reg 8 i address [7:0] $end
$upscope $end
$scope task schedule_jmp $end
$var reg 8 j new_addr [7:0] $end
$upscope $end
$upscope $end
$scope module pc $end
$var wire 32 k ip_next [31:0] $end
$var wire 1 $ pc_wr $end
$var reg 32 l ip [31:0] $end
$upscope $end
$scope module registers $end
$var wire 1 F clk $end
$var wire 5 m readreg1 [4:0] $end
$var wire 5 n readreg2 [4:0] $end
$var wire 1 ) regwr $end
$var wire 32 o writedata [31:0] $end
$var wire 5 p writereg [4:0] $end
$var reg 32 q outA [31:0] $end
$var reg 32 r outB [31:0] $end
$scope begin $unm_blk_27 $end
$var integer 32 s i [31:0] $end
$upscope $end
$upscope $end
$upscope $end
$enddefinitions $end
#0
$dumpvars
b100000 s
b0 r
b0 q
b0 p
b0 o
b0 n
b0 m
b0 l
b0 k
bx j
bx i
b1 h
b1 g
b0 f
b0 e
b1001010 d
bx c
b100000000 b
b100000000 a
b100000000 `
0_
b0 ^
1]
0\
b0 [
b0 Z
b11111111 Y
0X
b0 W
b0 V
b0 U
bz T
b0 S
b0 R
b0 Q
bz P
b0 O
bz N
b0 M
b0 L
b0 K
b0 J
b10 I
0H
0G
0F
b0 E
b0 D
0C
b0 B
b0 A
b10 @
b0 ?
0>
b0 =
b0 <
0;
b0 :
b0 9
bz 8
07
06
05
04
b0 3
b0 2
b0 1
b0 0
b0 /
0.
0-
b0 ,
b0 +
0*
0)
b0 (
b0 '
b0 &
1%
0$
b0 #
bz "
bz !
$end
#1
1$
1-
b1 A
b1 W
b1 ^
b1 i
1X
b100 Y
b100 j
b10000000000000000000000000010 Z
b0 c
1\
bz :
bz Q
1H
1G
1F
#2
0H
0F
#3
b10 ^
b101 i
b10 Y
b10 j
b10000000000000000000000000001 Z
b100 c
1X
b100 V
1F
#4
0F
#5
b11 ^
b11 i
b110 Y
b110 j
b10000000000000000000000000011 Z
b10 c
1X
b10 V
1F
#6
0F
#7
14
b100000000000000000000000000000001 A
b100000000000000000000000000000001 W
b0 Z
b110 c
0X
b110 V
1F
#8
0F
#9
1X
b11 Y
b11 j
b10 ^
1F
#10
0F
#11
b11 c
0X
b11 V
1F
#12
0F
#13
1X
b101 Y
b101 j
b1 ^
1F
#14
0F
#15
b101 c
0X
b101 V
1F
#16
0F
#17
1X
b1 Y
b1 j
b0 ^
1F
#18
0F
#19
b1 c
0X
b1 V
1F
